pytedit/__init__.py
pytedit/cli.py
pytedit/editor.py
pytedit/text_buffer.py
pytedit-0.1.1.dist-info/licenses/LICENCE
pytedit-0.1.1.dist-info/METADATA
pytedit-0.1.1.dist-info/WHEEL
pytedit-0.1.1.dist-info/entry_points.txt
pytedit-0.1.1.dist-info/top_level.txt
pytedit-0.1.1.dist-info/RECORD
